bda_chatbot-1.0.0.data/scripts/extract.py
bda_chatbot-1.0.0.data/scripts/grammar.py
bda_chatbot-1.0.0.data/scripts/lemm.py
bda_chatbot-1.0.0.data/scripts/normalize.py
bda_chatbot-1.0.0.data/scripts/stemm.py
bda_chatbot-1.0.0.data/scripts/stopwords.py
bda_core/__init__.py
bda_core/entities/__init__.py
bda_core/entities/file/__init__.py
bda_core/entities/file/json_handler.py
bda_core/entities/file/reader.py
bda_core/entities/file/res/custom_ch_grammar.txt
bda_core/entities/file/res/custom_ch_stopwords.txt
bda_core/entities/file/res/custom_ch_vocabular.txt
bda_core/entities/file/res/custom_en_stopwords.txt
bda_core/entities/file/res/custom_en_vocabular.txt
bda_core/entities/nlp/__init__.py
bda_core/entities/nlp/grammar.py
bda_core/entities/nlp/lemming.py
bda_core/entities/nlp/normalize.py
bda_core/entities/nlp/stemming.py
bda_core/entities/nlp/stopwords.py
bda_core/entities/prediction/__init__.py
bda_core/entities/prediction/similarity.py
bda_core/entities/stackexchange/__init__.py
bda_core/entities/stackexchange/utils.py
bda_core/entities/training/__init__.py
bda_core/entities/training/vectorizer.py
bda_core/entities/training/word2vec_trainer.py
bda_core/entities/wiki/__init__.py
bda_core/use_cases/__init__.py
bda_core/use_cases/file/__init__.py
bda_core/use_cases/file/extract_column.py
bda_core/use_cases/file/extract_json.py
bda_core/use_cases/log/__init__.py
bda_core/use_cases/log/log_info.py
bda_core/use_cases/nlp/__init__.py
bda_core/use_cases/nlp/correct_grammar.py
bda_core/use_cases/nlp/lemm_doc.py
bda_core/use_cases/nlp/normalize_doc.py
bda_core/use_cases/nlp/remove_stopwords.py
bda_core/use_cases/nlp/stemm_doc.py
bda_core/use_cases/prediction/__init__.py
bda_core/use_cases/prediction/utils.py
bda_core/use_cases/stackexchange/__init__.py
bda_core/use_cases/stackexchange/extract_questions_with_answers.py
bda_core/use_cases/training/__init__.py
bda_core/use_cases/training/model.py
bda_core/use_cases/wiki/__init__.py
bda_core/use_cases/wiki/articlefilter.py
bda_chatbot-1.0.0.dist-info/METADATA
bda_chatbot-1.0.0.dist-info/WHEEL
bda_chatbot-1.0.0.dist-info/top_level.txt
bda_chatbot-1.0.0.dist-info/RECORD
